{
  "item1": "The sun rises in the east and sets in the west.",
  "item2": "Reading books expands your knowledge and imagination.",
  "item3": "A cup of coffee in the morning helps me wake up.",
  "item4": "The rain fell softly on the green grass.",
  "item5": "She painted a beautiful landscape with vibrant colors.",
  "item6": "The children laughed and played in the park all day.",
  "item7": "Music can lift your spirits and soothe your mind.",
  "item8": "He cooked a delicious meal for his family last night.",
  "item9": "The mountain peak was covered in snow.",
  "item10": "Her smile brightened up the entire room.",
  "item11": "The dog chased its tail in circles.",
  "item12": "A gentle breeze made the leaves dance.",
  "item13": "They traveled to Paris for their honeymoon.",
  "item14": "The movie was both exciting and emotional.",
  "item15": "He wrote a letter to his best friend.",
  "item16": "The cake was sweet and moist.",
  "item17": "She wore a red dress to the party.",
  "item18": "The train arrived at the station on time.",
  "item19": "He solved the puzzle in just a few minutes.",
  "item20": "The stars twinkled brightly in the night sky.",
  "item21": "She found a lost kitten under the porch.",
  "item22": "The teacher explained the lesson clearly.",
  "item23": "He planted flowers in the garden every spring.",
  "item24": "The river flowed gently through the valley.",
  "item25": "She baked cookies for her classmates.",
  "item26": "The car stopped at the red light.",
  "item27": "He played the guitar at the concert.",
  "item28": "The library was quiet and peaceful.",
  "item29": "She drew a picture of her family.",
  "item30": "The baby giggled when tickled.",
  "item31": "He fixed the broken chair with glue.",
  "item32": "The butterfly landed on a yellow flower.",
  "item33": "She sang a song for her friends.",
  "item34": "The soup was hot and tasty.",
  "item35": "He watched the sunset from the balcony.",
  "item36": "The cat slept on the windowsill.",
  "item37": "She wrote a poem about nature.",
  "item38": "The clock struck twelve at midnight.",
  "item39": "He bought a new bicycle last week.",
  "item40": "The ice cream melted quickly in the sun.",
  "item41": "She listened to her favorite podcast.",
  "item42": "The bird built a nest in the tree.",
  "item43": "He painted the fence white.",
  "item44": "The rainbows appeared after the storm.",
  "item45": "She learned to play the piano.",
  "item46": "The boat sailed across the lake.",
  "item47": "He made a paper airplane and flew it.",
  "item48": "The cookies smelled wonderful in the oven.",
  "item49": "She danced gracefully on the stage.",
  "item50": "The dog barked at the mailman.",
  "item51": "He read a mystery novel before bed.",
  "item52": "The snowman wore a scarf and hat.",
  "item53": "She watered the plants every morning.",
  "item54": "The frog jumped into the pond.",
  "item55": "He drew a map of the city.",
  "item56": "The pizza was topped with cheese and pepperoni.",
  "item57": "She found a shell on the beach.",
  "item58": "The squirrel climbed the tall tree.",
  "item59": "He played chess with his grandfather.",
  "item60": "The clouds drifted slowly across the sky.",
  "item61": "She wore a warm coat in winter.",
  "item62": "The lemonade was cold and refreshing.",
  "item63": "He built a sandcastle by the sea.",
  "item64": "The owl hooted in the night.",
  "item65": "She made a wish on a shooting star.",
  "item66": "The horse galloped through the field.",
  "item67": "He played soccer with his friends.",
  "item68": "The apple pie was delicious.",
  "item69": "She wrote a story about adventure.",
  "item70": "The wind blew the leaves around.",
  "item71": "He caught a fish in the river.",
  "item72": "The moon shone brightly above.",
  "item73": "She wore a hat to protect herself from the sun.",
  "item74": "The rabbit hopped across the yard.",
  "item75": "He played video games on the weekend.",
  "item76": "The flowers bloomed in spring.",
  "item77": "She made a necklace out of beads.",
  "item78": "The pancakes were fluffy and sweet.",
  "item79": "He watched a documentary about space.",
  "item80": "The turtle swam in the pond.",
  "item81": "She drew a rainbow with crayons.",
  "item82": "The lion roared loudly in the zoo.",
  "item83": "He played the drums in a band.",
  "item84": "The strawberries were ripe and juicy.",
  "item85": "She wrote a thank you note.",
  "item86": "The airplane flew high above the clouds.",
  "item87": "He made a snow angel in the yard.",
  "item88": "The giraffe reached for the leaves.",
  "item89": "She read a poem aloud in class.",
  "item90": "The dolphin jumped out of the water.",
  "item91": "He played cards with his cousins.",
  "item92": "The spider spun a web in the corner.",
  "item93": "She wore a bracelet on her wrist.",
  "item94": "The popcorn popped in the microwave.",
  "item95": "He wrote a list of groceries.",
  "item96": "The kangaroo hopped across the field.",
  "item97": "She made a paper boat and floated it.",
  "item98": "The elephant splashed water with its trunk.",
  "item99": "He played the violin at the recital.",
  "item100": "The stars shone brightly in the sky."
}
